backuppy/__init__.py
backuppy/config.py
backuppy/location.py
backuppy/notifier.py
backuppy/plugin.py
backuppy/task.py
backuppy/cli/__init__.py
backuppy/cli/cli.py
backuppy/cli/input.py
backuppy/tests/__init__.py
backuppy/tests/test_config.py
backuppy/tests/test_integration.py
backuppy/tests/test_location.py
backuppy/tests/test_notifier.py
backuppy/tests/test_plugin.py
backuppy/tests/test_task.py
backuppy/tests/cli/__init__.py
backuppy/tests/cli/test_cli.py
backuppy/tests/cli/test_input.py
backuppy-0.4.0.data/data/LICENSE
backuppy-0.4.0.data/data/README.md
backuppy-0.4.0.data/data/VERSION
backuppy-0.4.0.data/data/requirements.txt
backuppy-0.4.0.data/scripts/backuppy
backuppy-0.4.0.dist-info/DESCRIPTION.rst
backuppy-0.4.0.dist-info/METADATA
backuppy-0.4.0.dist-info/RECORD
backuppy-0.4.0.dist-info/WHEEL
backuppy-0.4.0.dist-info/metadata.json
backuppy-0.4.0.dist-info/top_level.txt
