Metadata-Version: 2.0
Name: backuppy
Version: 0.4.0
Summary: Backuppy backs up and restores your data using rsync.
Home-page: https://github.com/bartfeenstra/backuppy
Author: Bart Feenstra
Author-email: UNKNOWN
License: MIT
Platform: UNKNOWN
Classifier: Environment :: Console
Classifier: Intended Audience :: System Administrators
Classifier: Topic :: Security :: Cryptography
Classifier: Topic :: System :: Archiving :: Backup
Classifier: Topic :: System :: Recovery Tools
Requires-Dist: paramiko (~=2.4.0)
Requires-Dist: pyaml (~=17.12.1)
